README.md
setup.py
pylogging_tools/__init__.py
pylogging_tools/main.py
pylogging_tools/tests/__init__.py
python_logging_tools.egg-info/PKG-INFO
python_logging_tools.egg-info/SOURCES.txt
python_logging_tools.egg-info/dependency_links.txt
python_logging_tools.egg-info/entry_points.txt
python_logging_tools.egg-info/requires.txt
python_logging_tools.egg-info/top_level.txt
tests/test_1.py