Metadata-Version: 2.1
Name: python-logging-tools
Version: 0.1.0
Summary: logging package
Home-page: https://github.com/MGS-Daniil
Author: Daniil10295
Author-email: chernyak.daniil.2010@gmail.com
Classifier: Programming Language :: Python :: 3
Classifier: License :: OSI Approved :: MIT License
Classifier: Operating System :: OS Independent
Requires-Dist: logging
Requires-Dist: colorama
